DDPathGenerator/__init__.py
DDPathGenerator/data.py
DDPathGenerator/literal.py
DDPathGenerator/naive_path_generator.py
DDPathGenerator/path_generator.py
ddpathgenerator-0.0.1.dist-info/licenses/LICENSE.md
ddpathgenerator-0.0.1.dist-info/METADATA
ddpathgenerator-0.0.1.dist-info/WHEEL
ddpathgenerator-0.0.1.dist-info/top_level.txt
ddpathgenerator-0.0.1.dist-info/RECORD
