Metadata-Version: 2.4
Name: DDPathGenerator
Version: 0.0.1
Summary: Tool for analyzing quantum circuits
Author-email: Vicente López-Oliva <voliva@uji.es>
License: Copyright (c) 2018 The Python Packaging Authority
Project-URL: Homepage, https://github.com/voliva-esp/DDPathGenerator
Project-URL: Issues, https://github.com/voliva-esp/DDPathGenerator/issues
Classifier: Programming Language :: Python :: 3
Classifier: Operating System :: OS Independent
Requires-Python: >=3.8, <4
License-File: LICENSE.md
Dynamic: license-file
Dynamic: requires-python
